dataclasses_collections/__init__.py
dataclasses_collections/_user_list.py
dataclasses_collections-0.0.0.dist-info/METADATA
dataclasses_collections-0.0.0.dist-info/WHEEL
dataclasses_collections-0.0.0.dist-info/top_level.txt
dataclasses_collections-0.0.0.dist-info/RECORD
